pypdfplot/__init__.py
pypdfplot/_version.py
pypdfplot/classes.py
pypdfplot/cli.py
pypdfplot/functions.py
pypdfplot/backend/__init__.py
pypdfplot/backend/backend_pypdf.py
pypdfplot/backend/unpack.py
pypdfplot-0.6.5.dist-info/LICENSE
pypdfplot-0.6.5.dist-info/METADATA
pypdfplot-0.6.5.dist-info/WHEEL
pypdfplot-0.6.5.dist-info/entry_points.txt
pypdfplot-0.6.5.dist-info/top_level.txt
pypdfplot-0.6.5.dist-info/RECORD
