Metadata-Version: 2.1
Name: pypdfplot
Version: 0.6.5
Summary: Saves plots as PDF with embedded generating script
Home-page: UNKNOWN
Author: Dirk van den Bekerom
Author-email: dcmvdbekerom@gmail.com
License: GPLv3
Project-URL: Documentation, https://pypdfplot.readthedocs.io/
Project-URL: GitHub, https://github.com/dcmvdbekerom/pypdfplot
Platform: UNKNOWN
Classifier: License :: OSI Approved :: GNU General Public License v3 (GPLv3)
Classifier: Development Status :: 4 - Beta
Classifier: Intended Audience :: Science/Research
Classifier: Programming Language :: Python
Classifier: Topic :: Multimedia :: Graphics
Classifier: Topic :: Scientific/Engineering :: Visualization
Requires-Dist: matplotlib
Requires-Dist: PyPDF4
